LICENSE
MANIFEST.in
README.md
requirements.txt
setup.cfg
setup.py
CMSMonitoring/NATS.py
CMSMonitoring/StompAMQ.py
CMSMonitoring/StompAMQ7.py
CMSMonitoring/Validator.py
CMSMonitoring/__init__.py
CMSMonitoring/cmsmonit_size.py
CMSMonitoring/datasources_list.py
CMSMonitoring/eos_path_size.py
CMSMonitoring/grafana_duplicator.py
CMSMonitoring/grafana_manager.py
CMSMonitoring/grafana_textpanel_propagation.py
CMSMonitoring/hs06corehr.py
CMSMonitoring/monit.py
CMSMonitoring/nats2.py
CMSMonitoring/nats3.py
CMSMonitoring/rucio_quotas.py
CMSMonitoring/scrutiny_plot.py
CMSMonitoring/jsonschemas/CRAB.schema
CMSMonitoring/jsonschemas/ClassAds.schema
CMSMonitoring/jsonschemas/GlideinWMS.schema
CMSMonitoring/jsonschemas/JobMonitoring.schema
CMSMonitoring/jsonschemas/SubmissionInfrastructure.schema
CMSMonitoring/jsonschemas/WMAgent.schema
CMSMonitoring/jsonschemas/XrootD.schema
bin/monit
cmsmonitoring_test.egg-info/PKG-INFO
cmsmonitoring_test.egg-info/SOURCES.txt
cmsmonitoring_test.egg-info/dependency_links.txt
cmsmonitoring_test.egg-info/requires.txt
cmsmonitoring_test.egg-info/top_level.txt
test/test_brokers.py
test/test_schemas.py
test/test_time.py