Metadata-Version: 2.1
Name: cmsmonitoring-test
Version: 0.6.2
Summary: CMS Monitoring utilities
Author: Ceyhun Uzunoglu
Author-email: ceyhunuzngl@gmail.com
License: MIT
Classifier: Programming Language :: Python
Classifier: Operating System :: OS Independent
Classifier: License :: OSI Approved :: MIT License
License-File: LICENSE
